mircato/__init__.py
mircato/configs/__init__.py
mircato/configs/logging.py
mircato/configs/models.py
mircato/configs/statistics.py
mircato/dicom/__init__.py
mircato/dicom/dicom_folder.py
mircato/models/__init__.py
mircato/segmentation/__init__.py
mircato/segmentation/core.py
mircato/statistics/__init__.py
mircato/statistics/aorta.py
mircato/statistics/body_and_tissues.py
mircato/statistics/centerline.py
mircato/statistics/contrast_detection.py
mircato/statistics/cpr.py
mircato/statistics/nifti.py
mircato/statistics/total.py
mircato/statistics/utils.py
mircato-0.1.0.dist-info/METADATA
mircato-0.1.0.dist-info/WHEEL
mircato-0.1.0.dist-info/entry_points.txt
mircato-0.1.0.dist-info/RECORD
