Metadata-Version: 2.3
Name: mircato
Version: 0.1.0
Summary: Add your description here
Requires-Python: <3.12,>=3.10
Requires-Dist: cloud-files==4.24.2
Requires-Dist: cloud-volume==8.33.0
Requires-Dist: dicom2nifti>=2.4.11
Requires-Dist: dynamic-network-architectures>=0.3.1
Requires-Dist: kimimaro==4.0.0
Requires-Dist: loguru>=0.7.2
Requires-Dist: monai==1.3.1
Requires-Dist: nibabel>=5.2.1
Requires-Dist: numpy==1.26.4
Requires-Dist: pydicom==2.4.4
Requires-Dist: scikit-image==0.23.2
Requires-Dist: scipy==1.13.1
Requires-Dist: simpleitk==2.3.1
Requires-Dist: threadpoolctl>=3.5.0
Requires-Dist: torch==2.3.1
Requires-Dist: xgboost==2.1.0
